{
  "neoforge:conditions": [
    {
      "type": "neoforge:and",
      "values": [
        {
          "type": "neoforge:not",
          "value": {
            "type": "neoforge:tag_empty",
            "tag": "c:stones"
          }
        }
      ]
    }
  ],
  "type": "minecraft:crafting_shaped",
  "category": "misc",
  "key": {
    "r": {
      "item": "minecraft:redstone_torch"
    },
    "s": {
      "tag": "c:stones"
    }
  },
  "pattern": [
    " r ",
    "rrr",
    "srs"
  ],
  "result": {
    "count": 1,
    "id": "yetanotherredstonegadgets:redstone_divider"
  }
}